README.txt
setup.cfg
setup.py
collective/__init__.py
collective.genericsetup.ldap.egg-info/PKG-INFO
collective.genericsetup.ldap.egg-info/SOURCES.txt
collective.genericsetup.ldap.egg-info/dependency_links.txt
collective.genericsetup.ldap.egg-info/entry_points.txt
collective.genericsetup.ldap.egg-info/namespace_packages.txt
collective.genericsetup.ldap.egg-info/not-zip-safe
collective.genericsetup.ldap.egg-info/requires.txt
collective.genericsetup.ldap.egg-info/top_level.txt
collective/genericsetup/__init__.py
collective/genericsetup/ldap/__init__.py
collective/genericsetup/ldap/configure.zcml
collective/genericsetup/ldap/exportimport.py
collective/genericsetup/ldap/interfaces.py
collective/genericsetup/ldap/tests.py
collective/genericsetup/ldap/version.txt
collective/genericsetup/ldap/xml/ldap_plugin.xml
docs/HISTORY.txt
docs/INSTALL.txt
docs/LICENSE.GPL
docs/LICENSE.txt
