Metadata-Version: 1.0
Name: collective.genericsetup.ldap
Version: 1.0dev-r81790
Summary: Extension for GenericSetup, support for LDAP and AD
Home-page: http://svn.plone.org/svn/collective/collective.genericsetup.ldap
Author: Anne Walther
Author-email: awello@gmail.com
License: GPL
Keywords: Zope Plone Python LDAP AD GenericSetup
Platform: UNKNOWN
Classifier: Framework :: Plone
Classifier: Programming Language :: Python
Classifier: Topic :: Software Development :: Libraries :: Python Modules
